setup.py
fangyu_pypitest.egg-info/PKG-INFO
fangyu_pypitest.egg-info/SOURCES.txt
fangyu_pypitest.egg-info/dependency_links.txt
fangyu_pypitest.egg-info/entry_points.txt
fangyu_pypitest.egg-info/not-zip-safe
fangyu_pypitest.egg-info/requires.txt
fangyu_pypitest.egg-info/top_level.txt
ray/__init__.py
ray/actor.py
ray/exceptions.py
ray/function_manager.py
ray/gcs_utils.py
ray/import_thread.py
ray/local_mode_manager.py
ray/log_monitor.py
ray/memory_monitor.py
ray/monitor.py
ray/node.py
ray/parameter.py
ray/profiling.py
ray/ray_constants.py
ray/remote_function.py
ray/reporter.py
ray/resource_spec.py
ray/runtime_context.py
ray/serialization.py
ray/services.py
ray/setup-dev.py
ray/signature.py
ray/state.py
ray/utils.py
ray/worker.py
ray/autoscaler/__init__.py
ray/autoscaler/autoscaler.py
ray/autoscaler/commands.py
ray/autoscaler/docker.py
ray/autoscaler/log_timer.py
ray/autoscaler/node_provider.py
ray/autoscaler/tags.py
ray/autoscaler/updater.py
ray/autoscaler/aws/__init__.py
ray/autoscaler/aws/config.py
ray/autoscaler/aws/node_provider.py
ray/autoscaler/gcp/__init__.py
ray/autoscaler/gcp/config.py
ray/autoscaler/gcp/node_provider.py
ray/autoscaler/local/__init__.py
ray/autoscaler/local/config.py
ray/autoscaler/local/node_provider.py
ray/cloudpickle/__init__.py
ray/cloudpickle/cloudpickle.py
ray/core/__init__.py
ray/core/generated/__init__.py
ray/core/src/__init__.py
ray/core/src/plasma/__init__.py
ray/core/src/ray/__init__.py
ray/core/src/ray/raylet/__init__.py
ray/dataframe/__init__.py
ray/experimental/__init__.py
ray/experimental/api.py
ray/experimental/async_api.py
ray/experimental/async_plasma.py
ray/experimental/dynamic_resources.py
ray/experimental/gcs_flush_policy.py
ray/experimental/internal_kv.py
ray/experimental/named_actors.py
ray/experimental/no_return.py
ray/experimental/queue.py
ray/experimental/signal.py
ray/experimental/tf_utils.py
ray/experimental/array/__init__.py
ray/experimental/array/distributed/__init__.py
ray/experimental/array/distributed/core.py
ray/experimental/array/distributed/linalg.py
ray/experimental/array/distributed/random.py
ray/experimental/array/remote/__init__.py
ray/experimental/array/remote/core.py
ray/experimental/array/remote/linalg.py
ray/experimental/array/remote/random.py
