Metadata-Version: 2.1
Name: fangyu-pypitest
Version: 0.8.0.dev4
Summary: A system for parallel and distributed Python that unifies the ML ecosystem.
Home-page: https://github.com/ray-project/ray
Author: Fangyu Wu
Author-email: fywu85@gmail.com
License: Apache 2.0
Keywords: ray distributed parallel machine-learning reinforcement-learning deep-learning python
Platform: UNKNOWN
Provides-Extra: dashboard
Provides-Extra: rllib
Provides-Extra: debug
